{
   "external_documents" : [
      {
         "location" : "http://id.loc.gov/authorities/subjects/sh86001590.marcxml.xml",
         "title" : "Library of Congress Authority record"
      }
   ],
   "title" : "Segesta (Extinct city)",
   "lock_version" : "7",
   "uri" : "/subjects/3743",
   "publish" : "true",
   "jsonmodel_type" : "subject",
   "created_by" : "web_services",
   "terms" : [
      {
         "jsonmodel_type" : "term",
         "created_by" : "web_services",
         "term" : "Segesta (Extinct city)",
         "vocabulary" : "/vocabularies/1",
         "term_type" : "geographic"
      }
   ],
   "source" : "LCCN",
   "vocabulary" : "/vocabularies/1",
   "authority_id" : "sh86001590"
}